fnr/__init__.py
fnr/context_loaders.py
fnr/fnr_cli.py
fnr/fnr_core.py
fnr-0.1.2.dist-info/METADATA
fnr-0.1.2.dist-info/RECORD
fnr-0.1.2.dist-info/WHEEL
fnr-0.1.2.dist-info/entry_points.txt
fnr-0.1.2.dist-info/top_level.txt
