Metadata-Version: 2.1
Name: fnr
Version: 0.1.2
Summary: A command line utility to find & replace text.
Home-page: https://github.com/collincchoy/fnr
Author: Collin Choy
Author-email: collinchoyccc@gmail.com
License: UNKNOWN
Platform: UNKNOWN
Classifier: Programming Language :: Python :: 3
